ex/__init__.py
ex/bqa_dgei.py
ex/bqa_ex.py
ex/bqa_res.py
ex/bqa_sim.py
ex/bqa_test.py
ex/mctest.py
ex/pymc_ex.py
probayes/__init__.py
probayes/cond_cov.py
probayes/dist.py
probayes/dist_ops.py
probayes/dist_utils.py
probayes/domain.py
probayes/func.py
probayes/manifold.py
probayes/prob.py
probayes/pscales.py
probayes/rf.py
probayes/rf_utils.py
probayes/rj.py
probayes/rj_utils.py
probayes/rv.py
probayes/rv_utils.py
probayes/sc.py
probayes/sc_utils.py
probayes/sj.py
probayes/sp.py
probayes/sp_utils.py
probayes/vtypes.py
probayes-0.0.3.dist-info/LICENSE
probayes-0.0.3.dist-info/METADATA
probayes-0.0.3.dist-info/WHEEL
probayes-0.0.3.dist-info/top_level.txt
probayes-0.0.3.dist-info/RECORD
