Metadata-Version: 2.1
Name: probayes
Version: 0.0.3
Summary: Probability package supporting multiple Bayesian methods including MCMC
Home-page: https://github.com/Bhumbra/probayes
Author: Bhumbra
Author-email: bhumbra@gmail.com
License: UNKNOWN
Platform: UNKNOWN
Requires-Dist: numpy
Requires-Dist: scipy
Requires-Dist: matplotlib
